volttron/driver/base/__init__.py
volttron/driver/base/config.py
volttron/driver/base/driver.py
volttron/driver/base/driver_exceptions.py
volttron/driver/base/driver_locks.py
volttron/driver/base/interfaces.py
volttron/driver/base/utils.py
volttron_lib_base_driver-2.0.0rc1.dist-info/LICENSE
volttron_lib_base_driver-2.0.0rc1.dist-info/METADATA
volttron_lib_base_driver-2.0.0rc1.dist-info/WHEEL
volttron_lib_base_driver-2.0.0rc1.dist-info/RECORD
