Metadata-Version: 2.3
Name: volttron-lib-base-driver
Version: 2.0.0rc1
Summary: Volttron Driver libraries used to support development within the Volttron Driver Framework.
License: Apache-2.0
Author: Mark Bonicillo
Author-email: volttron@pnnl.gov
Requires-Python: >=3.10,<4.0
Classifier: Intended Audience :: Developers
Classifier: Intended Audience :: Information Technology
Classifier: Intended Audience :: Other Audience
Classifier: Intended Audience :: Science/Research
Classifier: License :: OSI Approved :: Apache Software License
Classifier: Programming Language :: Python :: 3
Classifier: Programming Language :: Python :: 3.10
Classifier: Programming Language :: Python :: 3.11
Classifier: Programming Language :: Python :: 3.12
Classifier: Programming Language :: Python :: 3.13
Classifier: Programming Language :: Python :: 3 :: Only
Requires-Dist: pydantic (>=2.9.2)
Requires-Dist: pydantic-core (>=2.23.4)
Requires-Dist: volttron-core (>=2.0.0rc0)
Project-URL: Homepage, https://github.com/eclipse-volttron/volttron-lib-base-driver
Project-URL: Repository, https://github.com/eclipse-volttron/volttron-lib-base-driver
